doip_sdk/__init__.py
doip_sdk/base/__init__.py
doip_sdk/base/handler.py
doip_sdk/base/server.py
doip_sdk/constant.py
doip_sdk/model/__init__.py
doip_sdk/model/response.py
doip_sdk/selfsigned.py
doip_sdk/socket_reader.py
doip_sdk/utils.py
doip_sdk-0.0.9.dist-info/METADATA
doip_sdk-0.0.9.dist-info/WHEEL
doip_sdk-0.0.9.dist-info/RECORD
