Metadata-Version: 2.3
Name: doip_sdk
Version: 0.0.9
Summary: The SDK for the development of DOIP
Author: Triet Doan
Author-email: triet.doan@gwdg.de
Requires-Python: >=3.11,<4.0
Classifier: Development Status :: 4 - Beta
Classifier: Programming Language :: Python :: 3
Classifier: Topic :: Software Development :: Libraries :: Python Modules
Requires-Dist: cryptography (>=45.0.5,<46.0.0)
Requires-Dist: loguru (>=0.7.3,<0.8.0)
Requires-Dist: pydantic (>=2.11.7,<3.0.0)
